file_re-1.2.2.dist-info/METADATA
file_re-1.2.2.dist-info/WHEEL
file_re/__init__.py
file_re/_file_re.cpython-312-powerpc64le-linux-gnu.so
file_re/core.py
file_re/match.py
file_re-1.2.2.dist-info/RECORD
